[{"user": {"following_url": "https://api.github.com/users/npmccallum/following{/other_user}", "url": "https://api.github.com/users/npmccallum", "site_admin": false, "gists_url": "https://api.github.com/users/npmccallum/gists{/gist_id}", "node_id": "MDQ6VXNlcjI4ODMwNA==", "starred_url": "https://api.github.com/users/npmccallum/starred{/owner}{/repo}", "gravatar_id": "", "id": 288304, "events_url": "https://api.github.com/users/npmccallum/events{/privacy}", "avatar_url": "https://avatars2.githubusercontent.com/u/288304?v=4", "login": "npmccallum", "repos_url": "https://api.github.com/users/npmccallum/repos", "subscriptions_url": "https://api.github.com/users/npmccallum/subscriptions", "followers_url": "https://api.github.com/users/npmccallum/followers", "html_url": "https://github.com/npmccallum", "received_events_url": "https://api.github.com/users/npmccallum/received_events", "type": "User", "organizations_url": "https://api.github.com/users/npmccallum/orgs"}, "number": 1, "state": "closed", "labels": [], "author_association": "MEMBER", "title": "Finish initial setup", "node_id": "MDExOlB1bGxSZXF1ZXN0MzMwOTUxNTMw", "pull_request": {"html_url": "https://github.com/rust-vmm/kvm/pull/1", "diff_url": "https://github.com/rust-vmm/kvm/pull/1.diff", "url": "https://api.github.com/repos/rust-vmm/kvm/pulls/1", "patch_url": "https://github.com/rust-vmm/kvm/pull/1.patch"}, "comments": 1, "updated_at": "2019-10-22T13:20:55Z", "labels_url": "https://api.github.com/repos/rust-vmm/kvm/issues/1/labels{/name}", "comments_url": "https://api.github.com/repos/rust-vmm/kvm/issues/1/comments", "locked": false, "html_url": "https://github.com/rust-vmm/kvm/pull/1", "created_at": "2019-10-22T11:58:34Z", "body": "Signed-off-by: Nathaniel McCallum <npmccallum@redhat.com>", "url": "https://api.github.com/repos/rust-vmm/kvm/issues/1", "id": 510607010, "events_url": "https://api.github.com/repos/rust-vmm/kvm/issues/1/events", "closed_at": "2019-10-22T13:20:55Z", "milestone": null, "assignee": null, "repository_url": "https://api.github.com/repos/rust-vmm/kvm", "assignees": []}]