[{"user": {"following_url": "https://api.github.com/users/sameo/following{/other_user}", "url": "https://api.github.com/users/sameo", "site_admin": false, "gists_url": "https://api.github.com/users/sameo/gists{/gist_id}", "node_id": "MDQ6VXNlcjEwNDM4NjM=", "starred_url": "https://api.github.com/users/sameo/starred{/owner}{/repo}", "gravatar_id": "", "id": 1043863, "events_url": "https://api.github.com/users/sameo/events{/privacy}", "avatar_url": "https://avatars2.githubusercontent.com/u/1043863?v=4", "login": "sameo", "repos_url": "https://api.github.com/users/sameo/repos", "subscriptions_url": "https://api.github.com/users/sameo/subscriptions", "followers_url": "https://api.github.com/users/sameo/followers", "html_url": "https://github.com/sameo", "received_events_url": "https://api.github.com/users/sameo/received_events", "type": "User", "organizations_url": "https://api.github.com/users/sameo/orgs"}, "issue_url": "https://api.github.com/repos/rust-vmm/vm-virtio/issues/8", "body": "@andreeaflorescu Could you please have a look?", "updated_at": "2019-10-07T08:48:14Z", "url": "https://api.github.com/repos/rust-vmm/vm-virtio/issues/comments/538900729", "author_association": "MEMBER", "html_url": "https://github.com/rust-vmm/vm-virtio/pull/8#issuecomment-538900729", "created_at": "2019-10-07T08:48:14Z", "id": 538900729, "node_id": "MDEyOklzc3VlQ29tbWVudDUzODkwMDcyOQ=="}, {"user": {"following_url": "https://api.github.com/users/andreeaflorescu/following{/other_user}", "url": "https://api.github.com/users/andreeaflorescu", "site_admin": false, "gists_url": "https://api.github.com/users/andreeaflorescu/gists{/gist_id}", "node_id": "MDQ6VXNlcjI4MTU5NDQ=", "starred_url": "https://api.github.com/users/andreeaflorescu/starred{/owner}{/repo}", "gravatar_id": "", "id": 2815944, "events_url": "https://api.github.com/users/andreeaflorescu/events{/privacy}", "avatar_url": "https://avatars0.githubusercontent.com/u/2815944?v=4", "login": "andreeaflorescu", "repos_url": "https://api.github.com/users/andreeaflorescu/repos", "subscriptions_url": "https://api.github.com/users/andreeaflorescu/subscriptions", "followers_url": "https://api.github.com/users/andreeaflorescu/followers", "html_url": "https://github.com/andreeaflorescu", "received_events_url": "https://api.github.com/users/andreeaflorescu/received_events", "type": "User", "organizations_url": "https://api.github.com/users/andreeaflorescu/orgs"}, "issue_url": "https://api.github.com/repos/rust-vmm/vm-virtio/issues/8", "body": "@sameo it looks like this crate does not pass the tests any more. Before merging this PR we probably need to fix it. ", "updated_at": "2019-10-07T08:51:59Z", "url": "https://api.github.com/repos/rust-vmm/vm-virtio/issues/comments/538902081", "author_association": "MEMBER", "html_url": "https://github.com/rust-vmm/vm-virtio/pull/8#issuecomment-538902081", "created_at": "2019-10-07T08:51:59Z", "id": 538902081, "node_id": "MDEyOklzc3VlQ29tbWVudDUzODkwMjA4MQ=="}, {"user": {"following_url": "https://api.github.com/users/sameo/following{/other_user}", "url": "https://api.github.com/users/sameo", "site_admin": false, "gists_url": "https://api.github.com/users/sameo/gists{/gist_id}", "node_id": "MDQ6VXNlcjEwNDM4NjM=", "starred_url": "https://api.github.com/users/sameo/starred{/owner}{/repo}", "gravatar_id": "", "id": 1043863, "events_url": "https://api.github.com/users/sameo/events{/privacy}", "avatar_url": "https://avatars2.githubusercontent.com/u/1043863?v=4", "login": "sameo", "repos_url": "https://api.github.com/users/sameo/repos", "subscriptions_url": "https://api.github.com/users/sameo/subscriptions", "followers_url": "https://api.github.com/users/sameo/followers", "html_url": "https://github.com/sameo", "received_events_url": "https://api.github.com/users/sameo/received_events", "type": "User", "organizations_url": "https://api.github.com/users/sameo/orgs"}, "issue_url": "https://api.github.com/repos/rust-vmm/vm-virtio/issues/8", "body": "> @sameo it looks like this crate does not pass the tests any more. Before merging this PR we probably need to fix it.\r\n\r\nYep. Fixed and this PR is now rebased on top of the fix.", "updated_at": "2019-10-07T09:38:24Z", "url": "https://api.github.com/repos/rust-vmm/vm-virtio/issues/comments/538920348", "author_association": "MEMBER", "html_url": "https://github.com/rust-vmm/vm-virtio/pull/8#issuecomment-538920348", "created_at": "2019-10-07T09:38:24Z", "id": 538920348, "node_id": "MDEyOklzc3VlQ29tbWVudDUzODkyMDM0OA=="}]